Metadata-Version: 2.1
Name: proxylist
Version: 0.2.1
Summary: Package to manage list of proxy servers
Author-email: Gregory Petukhov <lorien@lorien.name>
License: The MIT License (MIT)
Project-URL: homepage, http://github.com/lorien/proxylist
Classifier: Programming Language :: Python
Classifier: Programming Language :: Python :: 3
Classifier: Programming Language :: Python :: 3.8
Classifier: Programming Language :: Python :: 3.9
Classifier: Programming Language :: Python :: 3.10
Classifier: Programming Language :: Python :: 3.11
Classifier: License :: OSI Approved :: MIT License
Classifier: Development Status :: 4 - Beta
Classifier: Intended Audience :: Developers
Classifier: Operating System :: OS Independent
Classifier: Topic :: Software Development :: Libraries :: Python Modules
Classifier: Topic :: Internet :: WWW/HTTP
Classifier: Typing :: Typed
Requires-Python: >=3.8
License-File: LICENSE
